{
  "https://thanhnien.vn/rss/dien-dan/van-hoa-giao-thong.rss": {
    "etag": null,
    "last_modified": null,
    "fetched_at": 1759683634,
    "status": 200,
    "error": ""
  },
  "https://thanhnien.vn/rss/kinh-te.rss": {
    "etag": null,
    "last_modified": null,
    "fetched_at": 1759683635,
    "status": 200,
    "error": "Response payload is not completed: <TransferEncodingError: 400, message='Not enough data to satisfy transfer length header.'>"
  },
  "https://thanhnien.vn/rss/kinh-te/kinh-te-xanh.rss": {
    "etag": null,
    "last_modified": null,
    "fetched_at": 1759683635,
    "status": 200,
    "error": ""
  },
  "https://thanhnien.vn/rss/the-gioi/kinh-te-the-gioi.rss": {
    "etag": null,
    "last_modified": null,
    "fetched_at": 1759683635,
    "status": 200,
    "error": ""
  },
  "https://thanhnien.vn/rss/van-hoa/mon-ngon-ha-noi.rss": {
    "etag": null,
    "last_modified": null,
    "fetched_at": 1759683634,
    "status": 200,
    "error": ""
  },
  "https://thanhnien.vn/rss/xe/xe-giao-thong.rss": {
    "etag": null,
    "last_modified": null,
    "fetched_at": 1759683635,
    "status": 200,
    "error": ""
  },
  "https://tienphong.vn/rss/dau-tu-165.rss": {
    "etag": "d391e3e8b733e672c3ae6a30e896a706",
    "last_modified": null,
    "fetched_at": 1759683634,
    "status": 200,
    "error": ""
  },
  "https://tienphong.vn/rss/do-thi-du-an-269.rss": {
    "etag": "8f78c4e47c9c46f0c3dfdd7c4875b8b6",
    "last_modified": null,
    "fetched_at": 1759683634,
    "status": 200,
    "error": ""
  },
  "https://tienphong.vn/rss/giao-thong-do-thi-410.rss": {
    "etag": "089df19158ba5f42691c637ea5949ff3",
    "last_modified": null,
    "fetched_at": 1759683634,
    "status": 200,
    "error": ""
  },
  "https://tienphong.vn/rss/kinh-te--thi-truong-411.rss": {
    "etag": "6914d17693e5b9e02341f1e3ac0c9072",
    "last_modified": null,
    "fetched_at": 1759683634,
    "status": 200,
    "error": ""
  },
  "https://tienphong.vn/rss/kinh-te-3.rss": {
    "etag": "5ba06db3a43aae25a172324e2067a90b",
    "last_modified": null,
    "fetched_at": 1759683634,
    "status": 200,
    "error": ""
  },
  "https://tienphong.vn/rss/nstd-dau-tu-245.rss": {
    "etag": "147a2adf3fa0ad1822d70f0b8b468a98",
    "last_modified": null,
    "fetched_at": 1759683325,
    "status": 200,
    "error": ""
  },
  "https://tienphong.vn/rss/nstd-giao-thong-do-thi-244.rss": {
    "etag": "3189e8df22ec5ccea90cf8ce9c655eb5",
    "last_modified": null,
    "fetched_at": 1759683634,
    "status": 200,
    "error": ""
  },
  "https://tienphong.vn/rss/nstd-moi-truong-313.rss": {
    "etag": "81ff7d24f37535f1f97134b4386a294d",
    "last_modified": null,
    "fetched_at": 1759683325,
    "status": 200,
    "error": ""
  },
  "https://tienphong.vn/rss/song-xanh-dau-tu-444.rss": {
    "etag": "96466474699c1eca0f6a1c04acfee295",
    "last_modified": null,
    "fetched_at": 1759683634,
    "status": 200,
    "error": ""
  },
  "https://vovlive.vn/rss/kinh-te/kinh-te-xanh": {
    "etag": null,
    "last_modified": null,
    "fetched_at": 1759683635,
    "status": 200,
    "error": ""
  },
  "https://vovlive.vn/rss/thoi-su/an-ninh-quoc-phong": {
    "etag": null,
    "last_modified": null,
    "fetched_at": 1759683635,
    "status": 200,
    "error": ""
  },
  "https://vovlive.vn/rss/thoi-su/moi-truong": {
    "etag": null,
    "last_modified": null,
    "fetched_at": 1759683635,
    "status": 200,
    "error": ""
  },
  "https://vovlive.vn/rss/tin-tuc/kinh-te": {
    "etag": null,
    "last_modified": null,
    "fetched_at": 1759683635,
    "status": 200,
    "error": ""
  },
  "https://vovlive.vn/rss/vov-giao-thong-do-thi/vov-giao-thong-nhip-cau-giao-thong": {
    "etag": null,
    "last_modified": null,
    "fetched_at": 1759683635,
    "status": 200,
    "error": ""
  },
  "https://vovlive.vn/rss/vov-giao-thong-hot-news/vov-giao-thong-nhat-ky-do-thi": {
    "etag": null,
    "last_modified": null,
    "fetched_at": 1759683635,
    "status": 200,
    "error": ""
  },
  "https://vovlive.vn/rss/vov-giao-thong/vov-giao-thong-do-thi": {
    "etag": null,
    "last_modified": null,
    "fetched_at": 1759683635,
    "status": 200,
    "error": ""
  },
  "https://vovlive.vn/rss/vov1-khoc-hoc-cong-nghe/vov1-tai-nguyen-va-moi-truong": {
    "etag": null,
    "last_modified": null,
    "fetched_at": 1759683635,
    "status": 200,
    "error": ""
  },
  "https://vovlive.vn/rss/vov1-kinh-te/vov1-dong-chay-kinh-te": {
    "etag": null,
    "last_modified": null,
    "fetched_at": 1759683635,
    "status": 200,
    "error": ""
  },
  "https://vovlive.vn/rss/vov1-noi-chinh/vov1-xay-dung-dang": {
    "etag": null,
    "last_modified": null,
    "fetched_at": 1759683635,
    "status": 200
  },
  "https://vovlive.vn/rss/vov1/vov1-kinh-te": {
    "etag": null,
    "last_modified": null,
    "fetched_at": 1759683635,
    "status": 200,
    "error": ""
  },
  "https://vovlive.vn/rss/vov5/vov5-ha-noi-ngan-nam": {
    "etag": null,
    "last_modified": null,
    "fetched_at": 1759683635,
    "status": 200
  },
  "https://vovlive.vn/rss/vov5/vov5-kinh-te": {
    "etag": null,
    "last_modified": null,
    "fetched_at": 1759683635,
    "status": 200,
    "error": ""
  },
  "https://www.sggp.org.vn/rss/anninhtrattu-2.rss": {
    "etag": null,
    "last_modified": null,
    "fetched_at": 1759683635,
    "status": 200
  },
  "https://www.sggp.org.vn/rss/dautukt-37.rss": {
    "etag": null,
    "last_modified": null,
    "fetched_at": 1759683635,
    "status": 200
  },
  "https://www.sggp.org.vn/rss/kinhte-89.rss": {
    "etag": null,
    "last_modified": null,
    "fetched_at": 1759683635,
    "status": 200
  },
  "https://www.sggp.org.vn/rss/kinhtedoisong24h-421.rss": {
    "etag": null,
    "last_modified": null,
    "fetched_at": 1759683635,
    "status": 200
  },
  "https://www.sggp.org.vn/rss/quoc-phong-an-ninh-518.rss": {
    "etag": null,
    "last_modified": null,
    "fetched_at": 1759683635,
    "status": 200
  },
  "https://www.sggp.org.vn/rss/xahoi-giaothong-3.rss": {
    "etag": null,
    "last_modified": null,
    "fetched_at": 1759683636,
    "status": 200
  },
  "https://www.sggp.org.vn/rss/xahoi-gt-525.rss": {
    "etag": null,
    "last_modified": null,
    "fetched_at": 1759683636,
    "status": 200
  },
  "https://www.sggp.org.vn/rss/xahoi-moitruong-52.rss": {
    "etag": null,
    "last_modified": null,
    "fetched_at": 1759683636,
    "status": 200
  },
  "https://www.sggp.org.vn/rss/xaydungdang-204.rss": {
    "etag": null,
    "last_modified": null,
    "fetched_at": 1759683636,
    "status": 200
  },
  "https://tieudung.kinhtedothi.vn/chinh-sach-quy-hoach.rss": {
    "etag": null,
    "last_modified": null,
    "fetched_at": 1759683641,
    "status": 200,
    "error": ""
  },
  "https://tieudung.kinhtedothi.vn/vat-lieu-xay-dung.rss": {
    "etag": null,
    "last_modified": null,
    "fetched_at": 1759683635,
    "status": 200,
    "error": ""
  },
  "https://en.vneconomy.vn/dau-tu-ha-tang.rss": {
    "etag": null,
    "last_modified": null,
    "fetched_at": 1759683634,
    "status": 200,
    "error": ""
  },
  "https://en.vneconomy.vn/dau-tu.rss": {
    "etag": null,
    "last_modified": null,
    "fetched_at": 1759683634,
    "status": 200,
    "error": ""
  },
  "https://en.vneconomy.vn/kinh-te-so.rss": {
    "etag": null,
    "last_modified": null,
    "fetched_at": 1759683634,
    "status": 200,
    "error": ""
  },
  "https://en.vneconomy.vn/kinh-te-xanh.rss": {
    "etag": null,
    "last_modified": null,
    "fetched_at": 1759683634,
    "status": 200,
    "error": ""
  }
}