{
  "https://thanhnien.vn/rss/dien-dan/van-hoa-giao-thong.rss": {
    "etag": null,
    "last_modified": null,
    "fetched_at": 1755931220,
    "status": 200
  },
  "https://thanhnien.vn/rss/kinh-te.rss": {
    "etag": null,
    "last_modified": null,
    "fetched_at": 1755931220,
    "status": 200
  },
  "https://thanhnien.vn/rss/kinh-te/kinh-te-xanh.rss": {
    "etag": null,
    "last_modified": null,
    "fetched_at": 1755931220,
    "status": 200
  },
  "https://thanhnien.vn/rss/the-gioi/kinh-te-the-gioi.rss": {
    "etag": null,
    "last_modified": null,
    "fetched_at": 1755931220,
    "status": 200
  },
  "https://thanhnien.vn/rss/van-hoa/mon-ngon-ha-noi.rss": {
    "etag": null,
    "last_modified": null,
    "fetched_at": 1755931220,
    "status": 200
  },
  "https://thanhnien.vn/rss/xe/xe-giao-thong.rss": {
    "etag": null,
    "last_modified": null,
    "fetched_at": 1755931220,
    "status": 200
  },
  "https://tienphong.vn/rss/dau-tu-165.rss": {
    "etag": "5495ac2c54ac5fc075d3c7e82c73b9eb",
    "last_modified": null,
    "fetched_at": 1755931219,
    "status": 200
  },
  "https://tienphong.vn/rss/do-thi-du-an-269.rss": {
    "etag": "4847c4144e0a81781fd964ea4ee21081",
    "last_modified": null,
    "fetched_at": 1755931219,
    "status": 200
  },
  "https://tienphong.vn/rss/giao-thong-do-thi-410.rss": {
    "etag": "eb8156bcbddfec7c8de8fa9ca41969d5",
    "last_modified": null,
    "fetched_at": 1755931219,
    "status": 200,
    "error": ""
  },
  "https://tienphong.vn/rss/kinh-te--thi-truong-411.rss": {
    "etag": "6a2cc08c40d5e314c972bf6029f7de82",
    "last_modified": null,
    "fetched_at": 1755931219,
    "status": 200,
    "error": ""
  },
  "https://tienphong.vn/rss/kinh-te-3.rss": {
    "etag": "03394612d8cd894ad2f11fdafa91421b",
    "last_modified": null,
    "fetched_at": 1755931219,
    "status": 200
  },
  "https://tienphong.vn/rss/nstd-dau-tu-245.rss": {
    "etag": "1b7f3215456f6a2292f28ccb08ba7a04",
    "last_modified": null,
    "fetched_at": 1755931219,
    "status": 200,
    "error": ""
  },
  "https://tienphong.vn/rss/nstd-giao-thong-do-thi-244.rss": {
    "etag": "970957a8daccadbc50549ae990a0cb29",
    "last_modified": null,
    "fetched_at": 1755931219,
    "status": 200,
    "error": ""
  },
  "https://tienphong.vn/rss/nstd-moi-truong-313.rss": {
    "etag": "834131aca3fa9c9d6d2855595bc53ec2",
    "last_modified": null,
    "fetched_at": 1755931219,
    "status": 200
  },
  "https://tienphong.vn/rss/song-xanh-dau-tu-444.rss": {
    "etag": "9b04f97ada05358fc83dbbf59eb3fef5",
    "last_modified": null,
    "fetched_at": 1755931219,
    "status": 200
  },
  "https://vovlive.vn/rss/kinh-te/kinh-te-xanh": {
    "etag": null,
    "last_modified": null,
    "fetched_at": 1755931220,
    "status": 200
  },
  "https://vovlive.vn/rss/thoi-su/an-ninh-quoc-phong": {
    "etag": null,
    "last_modified": null,
    "fetched_at": 1755931218,
    "status": 200
  },
  "https://vovlive.vn/rss/thoi-su/moi-truong": {
    "etag": null,
    "last_modified": null,
    "fetched_at": 1755931219,
    "status": 200
  },
  "https://vovlive.vn/rss/tin-tuc/kinh-te": {
    "etag": null,
    "last_modified": null,
    "fetched_at": 1755931222,
    "status": 200
  },
  "https://vovlive.vn/rss/vov-giao-thong-do-thi/vov-giao-thong-nhip-cau-giao-thong": {
    "etag": null,
    "last_modified": null,
    "fetched_at": 1755931219,
    "status": 200
  },
  "https://vovlive.vn/rss/vov-giao-thong-hot-news/vov-giao-thong-nhat-ky-do-thi": {
    "etag": null,
    "last_modified": null,
    "fetched_at": 1755931219,
    "status": 200
  },
  "https://vovlive.vn/rss/vov-giao-thong/vov-giao-thong-do-thi": {
    "etag": null,
    "last_modified": null,
    "fetched_at": 1755931219,
    "status": 200
  },
  "https://vovlive.vn/rss/vov1-khoc-hoc-cong-nghe/vov1-tai-nguyen-va-moi-truong": {
    "etag": null,
    "last_modified": null,
    "fetched_at": 1755931219,
    "status": 200
  },
  "https://vovlive.vn/rss/vov1-kinh-te/vov1-dong-chay-kinh-te": {
    "etag": null,
    "last_modified": null,
    "fetched_at": 1755931219,
    "status": 200
  },
  "https://vovlive.vn/rss/vov1-noi-chinh/vov1-xay-dung-dang": {
    "etag": null,
    "last_modified": null,
    "fetched_at": 1755931219,
    "status": 200
  },
  "https://vovlive.vn/rss/vov1/vov1-kinh-te": {
    "etag": null,
    "last_modified": null,
    "fetched_at": 1755931220,
    "status": 200
  },
  "https://vovlive.vn/rss/vov5/vov5-ha-noi-ngan-nam": {
    "etag": null,
    "last_modified": null,
    "fetched_at": 1755931220,
    "status": 200
  },
  "https://vovlive.vn/rss/vov5/vov5-kinh-te": {
    "etag": null,
    "last_modified": null,
    "fetched_at": 1755931220,
    "status": 200
  },
  "https://www.sggp.org.vn/rss/anninhtrattu-2.rss": {
    "etag": null,
    "last_modified": null,
    "fetched_at": 1755931220,
    "status": 200
  },
  "https://www.sggp.org.vn/rss/dautukt-37.rss": {
    "etag": null,
    "last_modified": null,
    "fetched_at": 1755931220,
    "status": 200
  },
  "https://www.sggp.org.vn/rss/kinhte-89.rss": {
    "etag": null,
    "last_modified": null,
    "fetched_at": 1755931220,
    "status": 200
  },
  "https://www.sggp.org.vn/rss/kinhtedoisong24h-421.rss": {
    "etag": null,
    "last_modified": null,
    "fetched_at": 1755931220,
    "status": 200
  },
  "https://www.sggp.org.vn/rss/quoc-phong-an-ninh-518.rss": {
    "etag": null,
    "last_modified": null,
    "fetched_at": 1755931220,
    "status": 200
  },
  "https://www.sggp.org.vn/rss/xahoi-giaothong-3.rss": {
    "etag": null,
    "last_modified": null,
    "fetched_at": 1755931220,
    "status": 200
  },
  "https://www.sggp.org.vn/rss/xahoi-gt-525.rss": {
    "etag": null,
    "last_modified": null,
    "fetched_at": 1755931220,
    "status": 200
  },
  "https://www.sggp.org.vn/rss/xahoi-moitruong-52.rss": {
    "etag": null,
    "last_modified": null,
    "fetched_at": 1755931220,
    "status": 200
  },
  "https://www.sggp.org.vn/rss/xaydungdang-204.rss": {
    "etag": null,
    "last_modified": null,
    "fetched_at": 1755931220,
    "status": 200
  },
  "https://tieudung.kinhtedothi.vn/chinh-sach-quy-hoach.rss": {
    "etag": null,
    "last_modified": null,
    "fetched_at": 1755931223,
    "status": 200,
    "error": ""
  },
  "https://tieudung.kinhtedothi.vn/vat-lieu-xay-dung.rss": {
    "etag": null,
    "last_modified": null,
    "fetched_at": 1755931220,
    "status": 200,
    "error": ""
  }
}