{
  "https://thanhnien.vn/rss/dien-dan/van-hoa-giao-thong.rss": {
    "etag": null,
    "last_modified": null,
    "fetched_at": 1757426937,
    "status": 200,
    "error": ""
  },
  "https://thanhnien.vn/rss/kinh-te.rss": {
    "etag": null,
    "last_modified": null,
    "fetched_at": 1757426938,
    "status": 200,
    "error": "Response payload is not completed: <TransferEncodingError: 400, message='Not enough data to satisfy transfer length header.'>"
  },
  "https://thanhnien.vn/rss/kinh-te/kinh-te-xanh.rss": {
    "etag": null,
    "last_modified": null,
    "fetched_at": 1757426938,
    "status": 200,
    "error": "Response payload is not completed: <TransferEncodingError: 400, message='Not enough data to satisfy transfer length header.'>"
  },
  "https://thanhnien.vn/rss/the-gioi/kinh-te-the-gioi.rss": {
    "etag": null,
    "last_modified": null,
    "fetched_at": 1757426938,
    "status": 200,
    "error": "Response payload is not completed: <TransferEncodingError: 400, message='Not enough data to satisfy transfer length header.'>"
  },
  "https://thanhnien.vn/rss/van-hoa/mon-ngon-ha-noi.rss": {
    "etag": null,
    "last_modified": null,
    "fetched_at": 1757426937,
    "status": 200,
    "error": ""
  },
  "https://thanhnien.vn/rss/xe/xe-giao-thong.rss": {
    "etag": null,
    "last_modified": null,
    "fetched_at": 1757426938,
    "status": 200,
    "error": "Response payload is not completed: <TransferEncodingError: 400, message='Not enough data to satisfy transfer length header.'>"
  },
  "https://tienphong.vn/rss/dau-tu-165.rss": {
    "etag": "70541661d523f69e7fcedec138c9a0a2",
    "last_modified": null,
    "fetched_at": 1757426937,
    "status": 200,
    "error": ""
  },
  "https://tienphong.vn/rss/do-thi-du-an-269.rss": {
    "etag": "36013ae02ec6bcf4cc35c8f95ecf49d6",
    "last_modified": null,
    "fetched_at": 1757426937,
    "status": 200,
    "error": ""
  },
  "https://tienphong.vn/rss/giao-thong-do-thi-410.rss": {
    "etag": "d19d4bc90e57d24ee2ea0bf02240a20e",
    "last_modified": null,
    "fetched_at": 1757426937,
    "status": 200,
    "error": ""
  },
  "https://tienphong.vn/rss/kinh-te--thi-truong-411.rss": {
    "etag": "651d8a8510adbc8dc63488d5680580df",
    "last_modified": null,
    "fetched_at": 1757426937,
    "status": 200,
    "error": ""
  },
  "https://tienphong.vn/rss/kinh-te-3.rss": {
    "etag": "b586e9b04ec6c535be262481ccc5f9a7",
    "last_modified": null,
    "fetched_at": 1757426937,
    "status": 200,
    "error": ""
  },
  "https://tienphong.vn/rss/nstd-dau-tu-245.rss": {
    "etag": "27fa519249e3d0b886d2f60fc451402b",
    "last_modified": null,
    "fetched_at": 1757426937,
    "status": 200,
    "error": ""
  },
  "https://tienphong.vn/rss/nstd-giao-thong-do-thi-244.rss": {
    "etag": "140df4239b50badaf8c5c796ba2d0df6",
    "last_modified": null,
    "fetched_at": 1757426937,
    "status": 200,
    "error": ""
  },
  "https://tienphong.vn/rss/nstd-moi-truong-313.rss": {
    "etag": "62d55ef53a6731b57f85379104ceb2f5",
    "last_modified": null,
    "fetched_at": 1757426937,
    "status": 200,
    "error": ""
  },
  "https://tienphong.vn/rss/song-xanh-dau-tu-444.rss": {
    "etag": "4c0727cfabbd75a7e7b1821145aec77e",
    "last_modified": null,
    "fetched_at": 1757426937,
    "status": 200,
    "error": ""
  },
  "https://vovlive.vn/rss/kinh-te/kinh-te-xanh": {
    "etag": null,
    "last_modified": null,
    "fetched_at": 1757426936,
    "status": 200
  },
  "https://vovlive.vn/rss/thoi-su/an-ninh-quoc-phong": {
    "etag": null,
    "last_modified": null,
    "fetched_at": 1757426936,
    "status": 200,
    "error": ""
  },
  "https://vovlive.vn/rss/thoi-su/moi-truong": {
    "etag": null,
    "last_modified": null,
    "fetched_at": 1757426937,
    "status": 200
  },
  "https://vovlive.vn/rss/tin-tuc/kinh-te": {
    "etag": null,
    "last_modified": null,
    "fetched_at": 1757426936,
    "status": 200,
    "error": ""
  },
  "https://vovlive.vn/rss/vov-giao-thong-do-thi/vov-giao-thong-nhip-cau-giao-thong": {
    "etag": null,
    "last_modified": null,
    "fetched_at": 1757426936,
    "status": 200,
    "error": ""
  },
  "https://vovlive.vn/rss/vov-giao-thong-hot-news/vov-giao-thong-nhat-ky-do-thi": {
    "etag": null,
    "last_modified": null,
    "fetched_at": 1757426936,
    "status": 200,
    "error": ""
  },
  "https://vovlive.vn/rss/vov-giao-thong/vov-giao-thong-do-thi": {
    "etag": null,
    "last_modified": null,
    "fetched_at": 1757426937,
    "status": 200
  },
  "https://vovlive.vn/rss/vov1-khoc-hoc-cong-nghe/vov1-tai-nguyen-va-moi-truong": {
    "etag": null,
    "last_modified": null,
    "fetched_at": 1757426937,
    "status": 200
  },
  "https://vovlive.vn/rss/vov1-kinh-te/vov1-dong-chay-kinh-te": {
    "etag": null,
    "last_modified": null,
    "fetched_at": 1757426937,
    "status": 200,
    "error": ""
  },
  "https://vovlive.vn/rss/vov1-noi-chinh/vov1-xay-dung-dang": {
    "etag": null,
    "last_modified": null,
    "fetched_at": 1757426937,
    "status": 200
  },
  "https://vovlive.vn/rss/vov1/vov1-kinh-te": {
    "etag": null,
    "last_modified": null,
    "fetched_at": 1757426937,
    "status": 200
  },
  "https://vovlive.vn/rss/vov5/vov5-ha-noi-ngan-nam": {
    "etag": null,
    "last_modified": null,
    "fetched_at": 1757426937,
    "status": 200
  },
  "https://vovlive.vn/rss/vov5/vov5-kinh-te": {
    "etag": null,
    "last_modified": null,
    "fetched_at": 1757426937,
    "status": 200
  },
  "https://www.sggp.org.vn/rss/anninhtrattu-2.rss": {
    "etag": null,
    "last_modified": null,
    "fetched_at": 1757426938,
    "status": 200
  },
  "https://www.sggp.org.vn/rss/dautukt-37.rss": {
    "etag": null,
    "last_modified": null,
    "fetched_at": 1757426938,
    "status": 200
  },
  "https://www.sggp.org.vn/rss/kinhte-89.rss": {
    "etag": null,
    "last_modified": null,
    "fetched_at": 1757426938,
    "status": 200
  },
  "https://www.sggp.org.vn/rss/kinhtedoisong24h-421.rss": {
    "etag": null,
    "last_modified": null,
    "fetched_at": 1757426938,
    "status": 200
  },
  "https://www.sggp.org.vn/rss/quoc-phong-an-ninh-518.rss": {
    "etag": null,
    "last_modified": null,
    "fetched_at": 1757426938,
    "status": 200
  },
  "https://www.sggp.org.vn/rss/xahoi-giaothong-3.rss": {
    "etag": null,
    "last_modified": null,
    "fetched_at": 1757426938,
    "status": 200
  },
  "https://www.sggp.org.vn/rss/xahoi-gt-525.rss": {
    "etag": null,
    "last_modified": null,
    "fetched_at": 1757426938,
    "status": 200
  },
  "https://www.sggp.org.vn/rss/xahoi-moitruong-52.rss": {
    "etag": null,
    "last_modified": null,
    "fetched_at": 1757426938,
    "status": 200
  },
  "https://www.sggp.org.vn/rss/xaydungdang-204.rss": {
    "etag": null,
    "last_modified": null,
    "fetched_at": 1757426938,
    "status": 200
  },
  "https://tieudung.kinhtedothi.vn/chinh-sach-quy-hoach.rss": {
    "etag": null,
    "last_modified": null,
    "fetched_at": 1757426962,
    "status": 200,
    "error": ""
  },
  "https://tieudung.kinhtedothi.vn/vat-lieu-xay-dung.rss": {
    "etag": null,
    "last_modified": null,
    "fetched_at": 1757426942,
    "status": 200,
    "error": ""
  }
}