{
  "https://thanhnien.vn/rss/dien-dan/van-hoa-giao-thong.rss": {
    "etag": null,
    "last_modified": null,
    "fetched_at": 1756036792,
    "status": 200
  },
  "https://thanhnien.vn/rss/kinh-te.rss": {
    "etag": null,
    "last_modified": null,
    "fetched_at": 1756036793,
    "status": 200,
    "error": ""
  },
  "https://thanhnien.vn/rss/kinh-te/kinh-te-xanh.rss": {
    "etag": null,
    "last_modified": null,
    "fetched_at": 1756036793,
    "status": 200,
    "error": ""
  },
  "https://thanhnien.vn/rss/the-gioi/kinh-te-the-gioi.rss": {
    "etag": null,
    "last_modified": null,
    "fetched_at": 1756036793,
    "status": 200
  },
  "https://thanhnien.vn/rss/van-hoa/mon-ngon-ha-noi.rss": {
    "etag": null,
    "last_modified": null,
    "fetched_at": 1756036792,
    "status": 200
  },
  "https://thanhnien.vn/rss/xe/xe-giao-thong.rss": {
    "etag": null,
    "last_modified": null,
    "fetched_at": 1756036793,
    "status": 200
  },
  "https://tienphong.vn/rss/dau-tu-165.rss": {
    "etag": "d72510af48836c8769f85c552571c2ce",
    "last_modified": null,
    "fetched_at": 1756036792,
    "status": 200
  },
  "https://tienphong.vn/rss/do-thi-du-an-269.rss": {
    "etag": "f258590de71e7519cd13aee8730dde47",
    "last_modified": null,
    "fetched_at": 1756036792,
    "status": 200
  },
  "https://tienphong.vn/rss/giao-thong-do-thi-410.rss": {
    "etag": "63e6c35bf2263923d588c56855c2e069",
    "last_modified": null,
    "fetched_at": 1756036792,
    "status": 200,
    "error": ""
  },
  "https://tienphong.vn/rss/kinh-te--thi-truong-411.rss": {
    "etag": "b6c5c87aaf7c5e0e64504a7bf3de6584",
    "last_modified": null,
    "fetched_at": 1756036792,
    "status": 200,
    "error": ""
  },
  "https://tienphong.vn/rss/kinh-te-3.rss": {
    "etag": "9a1777e91437d2865b2a7b56dbaec785",
    "last_modified": null,
    "fetched_at": 1756036488,
    "status": 200
  },
  "https://tienphong.vn/rss/nstd-dau-tu-245.rss": {
    "etag": "82a9c82c5f7160d84777694f7e833fa2",
    "last_modified": null,
    "fetched_at": 1756036792,
    "status": 200,
    "error": ""
  },
  "https://tienphong.vn/rss/nstd-giao-thong-do-thi-244.rss": {
    "etag": "3576eecafa4148b1a602fbd45e683716",
    "last_modified": null,
    "fetched_at": 1756036792,
    "status": 200,
    "error": ""
  },
  "https://tienphong.vn/rss/nstd-moi-truong-313.rss": {
    "etag": "28d3a167ba734cab487bdaad2577a2ca",
    "last_modified": null,
    "fetched_at": 1756036792,
    "status": 200
  },
  "https://tienphong.vn/rss/song-xanh-dau-tu-444.rss": {
    "etag": "ea1d29dcf5d5b4c51c6df9a90bba3ad3",
    "last_modified": null,
    "fetched_at": 1756036792,
    "status": 200
  },
  "https://vovlive.vn/rss/kinh-te/kinh-te-xanh": {
    "etag": null,
    "last_modified": null,
    "fetched_at": 1756036792,
    "status": 200
  },
  "https://vovlive.vn/rss/thoi-su/an-ninh-quoc-phong": {
    "etag": null,
    "last_modified": null,
    "fetched_at": 1756036792,
    "status": 200
  },
  "https://vovlive.vn/rss/thoi-su/moi-truong": {
    "etag": null,
    "last_modified": null,
    "fetched_at": 1756036791,
    "status": 200
  },
  "https://vovlive.vn/rss/tin-tuc/kinh-te": {
    "etag": null,
    "last_modified": null,
    "fetched_at": 1756036791,
    "status": 200
  },
  "https://vovlive.vn/rss/vov-giao-thong-do-thi/vov-giao-thong-nhip-cau-giao-thong": {
    "etag": null,
    "last_modified": null,
    "fetched_at": 1756036792,
    "status": 200
  },
  "https://vovlive.vn/rss/vov-giao-thong-hot-news/vov-giao-thong-nhat-ky-do-thi": {
    "etag": null,
    "last_modified": null,
    "fetched_at": 1756036792,
    "status": 200
  },
  "https://vovlive.vn/rss/vov-giao-thong/vov-giao-thong-do-thi": {
    "etag": null,
    "last_modified": null,
    "fetched_at": 1756036792,
    "status": 200
  },
  "https://vovlive.vn/rss/vov1-khoc-hoc-cong-nghe/vov1-tai-nguyen-va-moi-truong": {
    "etag": null,
    "last_modified": null,
    "fetched_at": 1756036792,
    "status": 200
  },
  "https://vovlive.vn/rss/vov1-kinh-te/vov1-dong-chay-kinh-te": {
    "etag": null,
    "last_modified": null,
    "fetched_at": 1756036792,
    "status": 200
  },
  "https://vovlive.vn/rss/vov1-noi-chinh/vov1-xay-dung-dang": {
    "etag": null,
    "last_modified": null,
    "fetched_at": 1756036792,
    "status": 200
  },
  "https://vovlive.vn/rss/vov1/vov1-kinh-te": {
    "etag": null,
    "last_modified": null,
    "fetched_at": 1756036792,
    "status": 200
  },
  "https://vovlive.vn/rss/vov5/vov5-ha-noi-ngan-nam": {
    "etag": null,
    "last_modified": null,
    "fetched_at": 1756036792,
    "status": 200
  },
  "https://vovlive.vn/rss/vov5/vov5-kinh-te": {
    "etag": null,
    "last_modified": null,
    "fetched_at": 1756036792,
    "status": 200
  },
  "https://www.sggp.org.vn/rss/anninhtrattu-2.rss": {
    "etag": null,
    "last_modified": null,
    "fetched_at": 1756036793,
    "status": 200
  },
  "https://www.sggp.org.vn/rss/dautukt-37.rss": {
    "etag": null,
    "last_modified": null,
    "fetched_at": 1756036793,
    "status": 200
  },
  "https://www.sggp.org.vn/rss/kinhte-89.rss": {
    "etag": null,
    "last_modified": null,
    "fetched_at": 1756036793,
    "status": 200
  },
  "https://www.sggp.org.vn/rss/kinhtedoisong24h-421.rss": {
    "etag": null,
    "last_modified": null,
    "fetched_at": 1756036793,
    "status": 200
  },
  "https://www.sggp.org.vn/rss/quoc-phong-an-ninh-518.rss": {
    "etag": null,
    "last_modified": null,
    "fetched_at": 1756036793,
    "status": 200
  },
  "https://www.sggp.org.vn/rss/xahoi-giaothong-3.rss": {
    "etag": null,
    "last_modified": null,
    "fetched_at": 1756036793,
    "status": 200
  },
  "https://www.sggp.org.vn/rss/xahoi-gt-525.rss": {
    "etag": null,
    "last_modified": null,
    "fetched_at": 1756036793,
    "status": 200
  },
  "https://www.sggp.org.vn/rss/xahoi-moitruong-52.rss": {
    "etag": null,
    "last_modified": null,
    "fetched_at": 1756036793,
    "status": 200
  },
  "https://www.sggp.org.vn/rss/xaydungdang-204.rss": {
    "etag": null,
    "last_modified": null,
    "fetched_at": 1756036793,
    "status": 200
  },
  "https://tieudung.kinhtedothi.vn/chinh-sach-quy-hoach.rss": {
    "etag": null,
    "last_modified": null,
    "fetched_at": 1756036807,
    "status": 200,
    "error": ""
  },
  "https://tieudung.kinhtedothi.vn/vat-lieu-xay-dung.rss": {
    "etag": null,
    "last_modified": null,
    "fetched_at": 1756036794,
    "status": 200,
    "error": ""
  }
}