{
  "https://thanhnien.vn/rss/dien-dan/van-hoa-giao-thong.rss": {
    "etag": null,
    "last_modified": null,
    "fetched_at": 1778370302,
    "status": 200,
    "error": ""
  },
  "https://thanhnien.vn/rss/kinh-te.rss": {
    "etag": null,
    "last_modified": null,
    "fetched_at": 1778370302,
    "status": 200,
    "error": ""
  },
  "https://thanhnien.vn/rss/kinh-te/kinh-te-xanh.rss": {
    "etag": null,
    "last_modified": null,
    "fetched_at": 1778370302,
    "status": 200,
    "error": ""
  },
  "https://thanhnien.vn/rss/the-gioi/kinh-te-the-gioi.rss": {
    "etag": null,
    "last_modified": null,
    "fetched_at": 1778370302,
    "status": 200,
    "error": "Response payload is not completed: <TransferEncodingError: 400, message='Not enough data to satisfy transfer length header.'>"
  },
  "https://thanhnien.vn/rss/van-hoa/mon-ngon-ha-noi.rss": {
    "etag": null,
    "last_modified": null,
    "fetched_at": 1778370302,
    "status": 200,
    "error": ""
  },
  "https://thanhnien.vn/rss/xe/xe-giao-thong.rss": {
    "etag": null,
    "last_modified": null,
    "fetched_at": 1778370302,
    "status": 200,
    "error": ""
  },
  "https://tienphong.vn/rss/dau-tu-165.rss": {
    "etag": "51487a76eeaa0fbc13a19d93a5db72d4",
    "last_modified": null,
    "fetched_at": 1778370302,
    "status": 200,
    "error": ""
  },
  "https://tienphong.vn/rss/do-thi-du-an-269.rss": {
    "etag": "c69dbeccf0f397e3342030458b1d7cc9",
    "last_modified": null,
    "fetched_at": 1778370302,
    "status": 200,
    "error": ""
  },
  "https://tienphong.vn/rss/giao-thong-do-thi-410.rss": {
    "etag": "fc43093ac353c3f16a4fa77aca318b2e",
    "last_modified": null,
    "fetched_at": 1778370302,
    "status": 200,
    "error": ""
  },
  "https://tienphong.vn/rss/kinh-te--thi-truong-411.rss": {
    "etag": "42cce28c7d42598e96debd8665d552ce",
    "last_modified": null,
    "fetched_at": 1778370302,
    "status": 200,
    "error": ""
  },
  "https://tienphong.vn/rss/kinh-te-3.rss": {
    "etag": "f11e634f4d2d1be57345a22fa9963493",
    "last_modified": null,
    "fetched_at": 1778370302,
    "status": 200,
    "error": ""
  },
  "https://tienphong.vn/rss/nstd-dau-tu-245.rss": {
    "etag": "560517131a6a0870a102cc30d825da23",
    "last_modified": null,
    "fetched_at": 1778370302,
    "status": 200,
    "error": ""
  },
  "https://tienphong.vn/rss/nstd-giao-thong-do-thi-244.rss": {
    "etag": "ae0b6359f7147d4a75b2a3562beed31b",
    "last_modified": null,
    "fetched_at": 1778370302,
    "status": 200,
    "error": ""
  },
  "https://tienphong.vn/rss/nstd-moi-truong-313.rss": {
    "etag": "6bddae432b518348d25808bfd170c87d",
    "last_modified": null,
    "fetched_at": 1778370302,
    "status": 200,
    "error": ""
  },
  "https://tienphong.vn/rss/song-xanh-dau-tu-444.rss": {
    "etag": "44e8ac715b409ca903556d1e608ce95c",
    "last_modified": null,
    "fetched_at": 1778370302,
    "status": 200,
    "error": ""
  },
  "https://vovlive.vn/rss/kinh-te/kinh-te-xanh": {
    "etag": null,
    "last_modified": null,
    "fetched_at": 1763520597,
    "status": 200,
    "error": ""
  },
  "https://vovlive.vn/rss/thoi-su/an-ninh-quoc-phong": {
    "etag": null,
    "last_modified": null,
    "fetched_at": 1763520597,
    "status": 200,
    "error": ""
  },
  "https://vovlive.vn/rss/thoi-su/moi-truong": {
    "etag": null,
    "last_modified": null,
    "fetched_at": 1763520597,
    "status": 200,
    "error": ""
  },
  "https://vovlive.vn/rss/tin-tuc/kinh-te": {
    "etag": null,
    "last_modified": null,
    "fetched_at": 1763520597,
    "status": 200,
    "error": ""
  },
  "https://vovlive.vn/rss/vov-giao-thong-do-thi/vov-giao-thong-nhip-cau-giao-thong": {
    "etag": null,
    "last_modified": null,
    "fetched_at": 1763520597,
    "status": 200,
    "error": ""
  },
  "https://vovlive.vn/rss/vov-giao-thong-hot-news/vov-giao-thong-nhat-ky-do-thi": {
    "etag": null,
    "last_modified": null,
    "fetched_at": 1763520597,
    "status": 200,
    "error": ""
  },
  "https://vovlive.vn/rss/vov-giao-thong/vov-giao-thong-do-thi": {
    "etag": null,
    "last_modified": null,
    "fetched_at": 1763520597,
    "status": 200,
    "error": ""
  },
  "https://vovlive.vn/rss/vov1-khoc-hoc-cong-nghe/vov1-tai-nguyen-va-moi-truong": {
    "etag": null,
    "last_modified": null,
    "fetched_at": 1763520597,
    "status": 200,
    "error": ""
  },
  "https://vovlive.vn/rss/vov1-kinh-te/vov1-dong-chay-kinh-te": {
    "etag": null,
    "last_modified": null,
    "fetched_at": 1763520597,
    "status": 200,
    "error": ""
  },
  "https://vovlive.vn/rss/vov1-noi-chinh/vov1-xay-dung-dang": {
    "etag": null,
    "last_modified": null,
    "fetched_at": 1763520597,
    "status": 200
  },
  "https://vovlive.vn/rss/vov1/vov1-kinh-te": {
    "etag": null,
    "last_modified": null,
    "fetched_at": 1763520597,
    "status": 200,
    "error": ""
  },
  "https://vovlive.vn/rss/vov5/vov5-ha-noi-ngan-nam": {
    "etag": null,
    "last_modified": null,
    "fetched_at": 1763520597,
    "status": 200
  },
  "https://vovlive.vn/rss/vov5/vov5-kinh-te": {
    "etag": null,
    "last_modified": null,
    "fetched_at": 1763520597,
    "status": 200,
    "error": ""
  },
  "https://www.sggp.org.vn/rss/anninhtrattu-2.rss": {
    "etag": null,
    "last_modified": null,
    "fetched_at": 1778370302,
    "status": 200,
    "error": ""
  },
  "https://www.sggp.org.vn/rss/dautukt-37.rss": {
    "etag": null,
    "last_modified": null,
    "fetched_at": 1778370302,
    "status": 200,
    "error": ""
  },
  "https://www.sggp.org.vn/rss/kinhte-89.rss": {
    "etag": null,
    "last_modified": null,
    "fetched_at": 1778370302,
    "status": 200
  },
  "https://www.sggp.org.vn/rss/kinhtedoisong24h-421.rss": {
    "etag": null,
    "last_modified": null,
    "fetched_at": 1778370302,
    "status": 200,
    "error": ""
  },
  "https://www.sggp.org.vn/rss/quoc-phong-an-ninh-518.rss": {
    "etag": null,
    "last_modified": null,
    "fetched_at": 1778370302,
    "status": 200,
    "error": ""
  },
  "https://www.sggp.org.vn/rss/xahoi-giaothong-3.rss": {
    "etag": null,
    "last_modified": null,
    "fetched_at": 1778370302,
    "status": 200
  },
  "https://www.sggp.org.vn/rss/xahoi-gt-525.rss": {
    "etag": null,
    "last_modified": null,
    "fetched_at": 1778370302,
    "status": 200
  },
  "https://www.sggp.org.vn/rss/xahoi-moitruong-52.rss": {
    "etag": null,
    "last_modified": null,
    "fetched_at": 1778370302,
    "status": 200
  },
  "https://www.sggp.org.vn/rss/xaydungdang-204.rss": {
    "etag": null,
    "last_modified": null,
    "fetched_at": 1778370302,
    "status": 200
  },
  "https://tieudung.kinhtedothi.vn/chinh-sach-quy-hoach.rss": {
    "etag": null,
    "last_modified": null,
    "fetched_at": 1777766973,
    "status": 200,
    "error": ""
  },
  "https://tieudung.kinhtedothi.vn/vat-lieu-xay-dung.rss": {
    "etag": null,
    "last_modified": null,
    "fetched_at": 1777766952,
    "status": 200,
    "error": ""
  },
  "https://en.vneconomy.vn/dau-tu-ha-tang.rss": {
    "etag": null,
    "last_modified": null,
    "fetched_at": 1759855826,
    "status": 200,
    "error": ""
  },
  "https://en.vneconomy.vn/dau-tu.rss": {
    "etag": null,
    "last_modified": null,
    "fetched_at": 1759855825,
    "status": 200,
    "error": ""
  },
  "https://en.vneconomy.vn/kinh-te-so.rss": {
    "etag": null,
    "last_modified": null,
    "fetched_at": 1759855825,
    "status": 200,
    "error": ""
  },
  "https://en.vneconomy.vn/kinh-te-xanh.rss": {
    "etag": null,
    "last_modified": null,
    "fetched_at": 1759855825,
    "status": 200,
    "error": ""
  }
}