{
  "https://thanhnien.vn/rss/dien-dan/van-hoa-giao-thong.rss": {
    "etag": null,
    "last_modified": null,
    "fetched_at": 1760347607,
    "status": 200,
    "error": ""
  },
  "https://thanhnien.vn/rss/kinh-te.rss": {
    "etag": null,
    "last_modified": null,
    "fetched_at": 1760347608,
    "status": 200,
    "error": "Response payload is not completed: <TransferEncodingError: 400, message='Not enough data to satisfy transfer length header.'>"
  },
  "https://thanhnien.vn/rss/kinh-te/kinh-te-xanh.rss": {
    "etag": null,
    "last_modified": null,
    "fetched_at": 1760347607,
    "status": 200,
    "error": "Response payload is not completed: <TransferEncodingError: 400, message='Not enough data to satisfy transfer length header.'>"
  },
  "https://thanhnien.vn/rss/the-gioi/kinh-te-the-gioi.rss": {
    "etag": null,
    "last_modified": null,
    "fetched_at": 1760347608,
    "status": 200,
    "error": "Response payload is not completed: <TransferEncodingError: 400, message='Not enough data to satisfy transfer length header.'>"
  },
  "https://thanhnien.vn/rss/van-hoa/mon-ngon-ha-noi.rss": {
    "etag": null,
    "last_modified": null,
    "fetched_at": 1760347607,
    "status": 200,
    "error": ""
  },
  "https://thanhnien.vn/rss/xe/xe-giao-thong.rss": {
    "etag": null,
    "last_modified": null,
    "fetched_at": 1760347608,
    "status": 200,
    "error": "Response payload is not completed: <TransferEncodingError: 400, message='Not enough data to satisfy transfer length header.'>"
  },
  "https://tienphong.vn/rss/dau-tu-165.rss": {
    "etag": "6708a15597ff656cd7b7a11c898e0bbc",
    "last_modified": null,
    "fetched_at": 1760347607,
    "status": 200,
    "error": ""
  },
  "https://tienphong.vn/rss/do-thi-du-an-269.rss": {
    "etag": "2a621dae8865a8f82e1fecb09906fe44",
    "last_modified": null,
    "fetched_at": 1760347607,
    "status": 200,
    "error": ""
  },
  "https://tienphong.vn/rss/giao-thong-do-thi-410.rss": {
    "etag": "13af8f3384ee19db9115ec31f0d722cc",
    "last_modified": null,
    "fetched_at": 1760347607,
    "status": 200,
    "error": ""
  },
  "https://tienphong.vn/rss/kinh-te--thi-truong-411.rss": {
    "etag": "7a65895a580b989ab40ced12330a5407",
    "last_modified": null,
    "fetched_at": 1760347607,
    "status": 200,
    "error": ""
  },
  "https://tienphong.vn/rss/kinh-te-3.rss": {
    "etag": "41b6bd634f19c2285b42d138f3a0c69c",
    "last_modified": null,
    "fetched_at": 1760347607,
    "status": 200,
    "error": ""
  },
  "https://tienphong.vn/rss/nstd-dau-tu-245.rss": {
    "etag": "e820a84a16829597f092437cffc9e861",
    "last_modified": null,
    "fetched_at": 1760347607,
    "status": 200,
    "error": ""
  },
  "https://tienphong.vn/rss/nstd-giao-thong-do-thi-244.rss": {
    "etag": "99f7e885e5c334cbc7cd7e0373440f0a",
    "last_modified": null,
    "fetched_at": 1760347607,
    "status": 200,
    "error": ""
  },
  "https://tienphong.vn/rss/nstd-moi-truong-313.rss": {
    "etag": "e4eadfe6fb02202d6c61100f5df419e5",
    "last_modified": null,
    "fetched_at": 1760347607,
    "status": 200,
    "error": ""
  },
  "https://tienphong.vn/rss/song-xanh-dau-tu-444.rss": {
    "etag": "d8e27178f600a66ec0a7e73dc589648d",
    "last_modified": null,
    "fetched_at": 1760347607,
    "status": 200,
    "error": ""
  },
  "https://vovlive.vn/rss/kinh-te/kinh-te-xanh": {
    "etag": null,
    "last_modified": null,
    "fetched_at": 1759737431,
    "status": 200,
    "error": ""
  },
  "https://vovlive.vn/rss/thoi-su/an-ninh-quoc-phong": {
    "etag": null,
    "last_modified": null,
    "fetched_at": 1759737431,
    "status": 200,
    "error": ""
  },
  "https://vovlive.vn/rss/thoi-su/moi-truong": {
    "etag": null,
    "last_modified": null,
    "fetched_at": 1759737431,
    "status": 200,
    "error": ""
  },
  "https://vovlive.vn/rss/tin-tuc/kinh-te": {
    "etag": null,
    "last_modified": null,
    "fetched_at": 1759737431,
    "status": 200,
    "error": ""
  },
  "https://vovlive.vn/rss/vov-giao-thong-do-thi/vov-giao-thong-nhip-cau-giao-thong": {
    "etag": null,
    "last_modified": null,
    "fetched_at": 1759737431,
    "status": 200,
    "error": ""
  },
  "https://vovlive.vn/rss/vov-giao-thong-hot-news/vov-giao-thong-nhat-ky-do-thi": {
    "etag": null,
    "last_modified": null,
    "fetched_at": 1759737431,
    "status": 200,
    "error": ""
  },
  "https://vovlive.vn/rss/vov-giao-thong/vov-giao-thong-do-thi": {
    "etag": null,
    "last_modified": null,
    "fetched_at": 1759737431,
    "status": 200,
    "error": ""
  },
  "https://vovlive.vn/rss/vov1-khoc-hoc-cong-nghe/vov1-tai-nguyen-va-moi-truong": {
    "etag": null,
    "last_modified": null,
    "fetched_at": 1759737432,
    "status": 200,
    "error": ""
  },
  "https://vovlive.vn/rss/vov1-kinh-te/vov1-dong-chay-kinh-te": {
    "etag": null,
    "last_modified": null,
    "fetched_at": 1759737432,
    "status": 200,
    "error": ""
  },
  "https://vovlive.vn/rss/vov1-noi-chinh/vov1-xay-dung-dang": {
    "etag": null,
    "last_modified": null,
    "fetched_at": 1759737432,
    "status": 200
  },
  "https://vovlive.vn/rss/vov1/vov1-kinh-te": {
    "etag": null,
    "last_modified": null,
    "fetched_at": 1759737432,
    "status": 200,
    "error": ""
  },
  "https://vovlive.vn/rss/vov5/vov5-ha-noi-ngan-nam": {
    "etag": null,
    "last_modified": null,
    "fetched_at": 1759737433,
    "status": 200
  },
  "https://vovlive.vn/rss/vov5/vov5-kinh-te": {
    "etag": null,
    "last_modified": null,
    "fetched_at": 1759737432,
    "status": 200,
    "error": ""
  },
  "https://www.sggp.org.vn/rss/anninhtrattu-2.rss": {
    "etag": null,
    "last_modified": null,
    "fetched_at": 1760347607,
    "status": 200
  },
  "https://www.sggp.org.vn/rss/dautukt-37.rss": {
    "etag": null,
    "last_modified": null,
    "fetched_at": 1760347607,
    "status": 200
  },
  "https://www.sggp.org.vn/rss/kinhte-89.rss": {
    "etag": null,
    "last_modified": null,
    "fetched_at": 1760347607,
    "status": 200
  },
  "https://www.sggp.org.vn/rss/kinhtedoisong24h-421.rss": {
    "etag": null,
    "last_modified": null,
    "fetched_at": 1760347607,
    "status": 200
  },
  "https://www.sggp.org.vn/rss/quoc-phong-an-ninh-518.rss": {
    "etag": null,
    "last_modified": null,
    "fetched_at": 1760347607,
    "status": 200
  },
  "https://www.sggp.org.vn/rss/xahoi-giaothong-3.rss": {
    "etag": null,
    "last_modified": null,
    "fetched_at": 1760347607,
    "status": 200
  },
  "https://www.sggp.org.vn/rss/xahoi-gt-525.rss": {
    "etag": null,
    "last_modified": null,
    "fetched_at": 1760347607,
    "status": 200
  },
  "https://www.sggp.org.vn/rss/xahoi-moitruong-52.rss": {
    "etag": null,
    "last_modified": null,
    "fetched_at": 1760347607,
    "status": 200
  },
  "https://www.sggp.org.vn/rss/xaydungdang-204.rss": {
    "etag": null,
    "last_modified": null,
    "fetched_at": 1760347607,
    "status": 200
  },
  "https://tieudung.kinhtedothi.vn/chinh-sach-quy-hoach.rss": {
    "etag": null,
    "last_modified": null,
    "fetched_at": 1760347612,
    "status": 200,
    "error": ""
  },
  "https://tieudung.kinhtedothi.vn/vat-lieu-xay-dung.rss": {
    "etag": null,
    "last_modified": null,
    "fetched_at": 1760347607,
    "status": 200,
    "error": ""
  },
  "https://en.vneconomy.vn/dau-tu-ha-tang.rss": {
    "etag": null,
    "last_modified": null,
    "fetched_at": 1759855826,
    "status": 200,
    "error": ""
  },
  "https://en.vneconomy.vn/dau-tu.rss": {
    "etag": null,
    "last_modified": null,
    "fetched_at": 1759855825,
    "status": 200,
    "error": ""
  },
  "https://en.vneconomy.vn/kinh-te-so.rss": {
    "etag": null,
    "last_modified": null,
    "fetched_at": 1759855825,
    "status": 200,
    "error": ""
  },
  "https://en.vneconomy.vn/kinh-te-xanh.rss": {
    "etag": null,
    "last_modified": null,
    "fetched_at": 1759855825,
    "status": 200,
    "error": ""
  }
}