{
  "https://thanhnien.vn/rss/dien-dan/van-hoa-giao-thong.rss": {
    "etag": null,
    "last_modified": null,
    "fetched_at": 1760601418,
    "status": 200,
    "error": ""
  },
  "https://thanhnien.vn/rss/kinh-te.rss": {
    "etag": null,
    "last_modified": null,
    "fetched_at": 1760601418,
    "status": 200,
    "error": ""
  },
  "https://thanhnien.vn/rss/kinh-te/kinh-te-xanh.rss": {
    "etag": null,
    "last_modified": null,
    "fetched_at": 1760601418,
    "status": 200,
    "error": ""
  },
  "https://thanhnien.vn/rss/the-gioi/kinh-te-the-gioi.rss": {
    "etag": null,
    "last_modified": null,
    "fetched_at": 1760601418,
    "status": 200,
    "error": "Response payload is not completed: <TransferEncodingError: 400, message='Not enough data to satisfy transfer length header.'>"
  },
  "https://thanhnien.vn/rss/van-hoa/mon-ngon-ha-noi.rss": {
    "etag": null,
    "last_modified": null,
    "fetched_at": 1760601418,
    "status": 200,
    "error": ""
  },
  "https://thanhnien.vn/rss/xe/xe-giao-thong.rss": {
    "etag": null,
    "last_modified": null,
    "fetched_at": 1760601418,
    "status": 200,
    "error": "Response payload is not completed: <TransferEncodingError: 400, message='Not enough data to satisfy transfer length header.'>"
  },
  "https://tienphong.vn/rss/dau-tu-165.rss": {
    "etag": "aad38efa0216f2837be6b12bf71bf559",
    "last_modified": null,
    "fetched_at": 1760601418,
    "status": 200,
    "error": ""
  },
  "https://tienphong.vn/rss/do-thi-du-an-269.rss": {
    "etag": "2c06ab74ba6a7d2ac90da431f65159ad",
    "last_modified": null,
    "fetched_at": 1760601418,
    "status": 200,
    "error": ""
  },
  "https://tienphong.vn/rss/giao-thong-do-thi-410.rss": {
    "etag": "19e2ed9164f035988de1d1dff9403353",
    "last_modified": null,
    "fetched_at": 1760601418,
    "status": 200,
    "error": ""
  },
  "https://tienphong.vn/rss/kinh-te--thi-truong-411.rss": {
    "etag": "32cc98f41dde2f7eba354b3521fbdefa",
    "last_modified": null,
    "fetched_at": 1760601418,
    "status": 200,
    "error": ""
  },
  "https://tienphong.vn/rss/kinh-te-3.rss": {
    "etag": "c29996c851b8b9e0a1c48935e62524e0",
    "last_modified": null,
    "fetched_at": 1760601418,
    "status": 200,
    "error": ""
  },
  "https://tienphong.vn/rss/nstd-dau-tu-245.rss": {
    "etag": "8f6b5ac9699e956b9c894a12b0d91ef6",
    "last_modified": null,
    "fetched_at": 1760601418,
    "status": 200,
    "error": ""
  },
  "https://tienphong.vn/rss/nstd-giao-thong-do-thi-244.rss": {
    "etag": "4e5fd128eef1e93e74d859a4b96bce28",
    "last_modified": null,
    "fetched_at": 1760601418,
    "status": 200,
    "error": ""
  },
  "https://tienphong.vn/rss/nstd-moi-truong-313.rss": {
    "etag": "dc290d111aa32561acb556020ea42251",
    "last_modified": null,
    "fetched_at": 1760601418,
    "status": 200,
    "error": ""
  },
  "https://tienphong.vn/rss/song-xanh-dau-tu-444.rss": {
    "etag": "fc5d9fb9dac6264cb212823bfda0e10e",
    "last_modified": null,
    "fetched_at": 1760601418,
    "status": 200,
    "error": ""
  },
  "https://vovlive.vn/rss/kinh-te/kinh-te-xanh": {
    "etag": null,
    "last_modified": null,
    "fetched_at": 1759737431,
    "status": 200,
    "error": ""
  },
  "https://vovlive.vn/rss/thoi-su/an-ninh-quoc-phong": {
    "etag": null,
    "last_modified": null,
    "fetched_at": 1759737431,
    "status": 200,
    "error": ""
  },
  "https://vovlive.vn/rss/thoi-su/moi-truong": {
    "etag": null,
    "last_modified": null,
    "fetched_at": 1759737431,
    "status": 200,
    "error": ""
  },
  "https://vovlive.vn/rss/tin-tuc/kinh-te": {
    "etag": null,
    "last_modified": null,
    "fetched_at": 1759737431,
    "status": 200,
    "error": ""
  },
  "https://vovlive.vn/rss/vov-giao-thong-do-thi/vov-giao-thong-nhip-cau-giao-thong": {
    "etag": null,
    "last_modified": null,
    "fetched_at": 1759737431,
    "status": 200,
    "error": ""
  },
  "https://vovlive.vn/rss/vov-giao-thong-hot-news/vov-giao-thong-nhat-ky-do-thi": {
    "etag": null,
    "last_modified": null,
    "fetched_at": 1759737431,
    "status": 200,
    "error": ""
  },
  "https://vovlive.vn/rss/vov-giao-thong/vov-giao-thong-do-thi": {
    "etag": null,
    "last_modified": null,
    "fetched_at": 1759737431,
    "status": 200,
    "error": ""
  },
  "https://vovlive.vn/rss/vov1-khoc-hoc-cong-nghe/vov1-tai-nguyen-va-moi-truong": {
    "etag": null,
    "last_modified": null,
    "fetched_at": 1759737432,
    "status": 200,
    "error": ""
  },
  "https://vovlive.vn/rss/vov1-kinh-te/vov1-dong-chay-kinh-te": {
    "etag": null,
    "last_modified": null,
    "fetched_at": 1759737432,
    "status": 200,
    "error": ""
  },
  "https://vovlive.vn/rss/vov1-noi-chinh/vov1-xay-dung-dang": {
    "etag": null,
    "last_modified": null,
    "fetched_at": 1759737432,
    "status": 200
  },
  "https://vovlive.vn/rss/vov1/vov1-kinh-te": {
    "etag": null,
    "last_modified": null,
    "fetched_at": 1759737432,
    "status": 200,
    "error": ""
  },
  "https://vovlive.vn/rss/vov5/vov5-ha-noi-ngan-nam": {
    "etag": null,
    "last_modified": null,
    "fetched_at": 1759737433,
    "status": 200
  },
  "https://vovlive.vn/rss/vov5/vov5-kinh-te": {
    "etag": null,
    "last_modified": null,
    "fetched_at": 1759737432,
    "status": 200,
    "error": ""
  },
  "https://www.sggp.org.vn/rss/anninhtrattu-2.rss": {
    "etag": null,
    "last_modified": null,
    "fetched_at": 1760601417,
    "status": 200
  },
  "https://www.sggp.org.vn/rss/dautukt-37.rss": {
    "etag": null,
    "last_modified": null,
    "fetched_at": 1760601417,
    "status": 200
  },
  "https://www.sggp.org.vn/rss/kinhte-89.rss": {
    "etag": null,
    "last_modified": null,
    "fetched_at": 1760601417,
    "status": 200
  },
  "https://www.sggp.org.vn/rss/kinhtedoisong24h-421.rss": {
    "etag": null,
    "last_modified": null,
    "fetched_at": 1760601417,
    "status": 200
  },
  "https://www.sggp.org.vn/rss/quoc-phong-an-ninh-518.rss": {
    "etag": null,
    "last_modified": null,
    "fetched_at": 1760601417,
    "status": 200
  },
  "https://www.sggp.org.vn/rss/xahoi-giaothong-3.rss": {
    "etag": null,
    "last_modified": null,
    "fetched_at": 1760601417,
    "status": 200
  },
  "https://www.sggp.org.vn/rss/xahoi-gt-525.rss": {
    "etag": null,
    "last_modified": null,
    "fetched_at": 1760601417,
    "status": 200
  },
  "https://www.sggp.org.vn/rss/xahoi-moitruong-52.rss": {
    "etag": null,
    "last_modified": null,
    "fetched_at": 1760601418,
    "status": 200
  },
  "https://www.sggp.org.vn/rss/xaydungdang-204.rss": {
    "etag": null,
    "last_modified": null,
    "fetched_at": 1760601418,
    "status": 200
  },
  "https://tieudung.kinhtedothi.vn/chinh-sach-quy-hoach.rss": {
    "etag": null,
    "last_modified": null,
    "fetched_at": 1760601422,
    "status": 200,
    "error": ""
  },
  "https://tieudung.kinhtedothi.vn/vat-lieu-xay-dung.rss": {
    "etag": null,
    "last_modified": null,
    "fetched_at": 1760601418,
    "status": 200,
    "error": ""
  },
  "https://en.vneconomy.vn/dau-tu-ha-tang.rss": {
    "etag": null,
    "last_modified": null,
    "fetched_at": 1759855826,
    "status": 200,
    "error": ""
  },
  "https://en.vneconomy.vn/dau-tu.rss": {
    "etag": null,
    "last_modified": null,
    "fetched_at": 1759855825,
    "status": 200,
    "error": ""
  },
  "https://en.vneconomy.vn/kinh-te-so.rss": {
    "etag": null,
    "last_modified": null,
    "fetched_at": 1759855825,
    "status": 200,
    "error": ""
  },
  "https://en.vneconomy.vn/kinh-te-xanh.rss": {
    "etag": null,
    "last_modified": null,
    "fetched_at": 1759855825,
    "status": 200,
    "error": ""
  }
}