{
  "https://thanhnien.vn/rss/dien-dan/van-hoa-giao-thong.rss": {
    "etag": null,
    "last_modified": null,
    "fetched_at": 1756395794,
    "status": 200,
    "error": ""
  },
  "https://thanhnien.vn/rss/kinh-te.rss": {
    "etag": null,
    "last_modified": null,
    "fetched_at": 1756395795,
    "status": 200,
    "error": ""
  },
  "https://thanhnien.vn/rss/kinh-te/kinh-te-xanh.rss": {
    "etag": null,
    "last_modified": null,
    "fetched_at": 1756395795,
    "status": 200,
    "error": "Response payload is not completed: <TransferEncodingError: 400, message='Not enough data to satisfy transfer length header.'>"
  },
  "https://thanhnien.vn/rss/the-gioi/kinh-te-the-gioi.rss": {
    "etag": null,
    "last_modified": null,
    "fetched_at": 1756395795,
    "status": 200,
    "error": "Response payload is not completed: <TransferEncodingError: 400, message='Not enough data to satisfy transfer length header.'>"
  },
  "https://thanhnien.vn/rss/van-hoa/mon-ngon-ha-noi.rss": {
    "etag": null,
    "last_modified": null,
    "fetched_at": 1756395794,
    "status": 200,
    "error": ""
  },
  "https://thanhnien.vn/rss/xe/xe-giao-thong.rss": {
    "etag": null,
    "last_modified": null,
    "fetched_at": 1756395795,
    "status": 200,
    "error": "Response payload is not completed: <TransferEncodingError: 400, message='Not enough data to satisfy transfer length header.'>"
  },
  "https://tienphong.vn/rss/dau-tu-165.rss": {
    "etag": "0883813a7beb0858e5ac5d26d50da7b6",
    "last_modified": null,
    "fetched_at": 1756395794,
    "status": 200
  },
  "https://tienphong.vn/rss/do-thi-du-an-269.rss": {
    "etag": "c41a6739648c7f4f2017f8701e84d727",
    "last_modified": null,
    "fetched_at": 1756395794,
    "status": 200
  },
  "https://tienphong.vn/rss/giao-thong-do-thi-410.rss": {
    "etag": "498d1d83025966082b13295cc4084108",
    "last_modified": null,
    "fetched_at": 1756395794,
    "status": 200,
    "error": ""
  },
  "https://tienphong.vn/rss/kinh-te--thi-truong-411.rss": {
    "etag": "925308946a747f7679adfae923c87666",
    "last_modified": null,
    "fetched_at": 1756395794,
    "status": 200,
    "error": ""
  },
  "https://tienphong.vn/rss/kinh-te-3.rss": {
    "etag": "0bf00b3cec54f679c6df14a6bdd2724f",
    "last_modified": null,
    "fetched_at": 1756395794,
    "status": 200
  },
  "https://tienphong.vn/rss/nstd-dau-tu-245.rss": {
    "etag": "2a5177f941321576d5395fab09a309b3",
    "last_modified": null,
    "fetched_at": 1756395794,
    "status": 200,
    "error": ""
  },
  "https://tienphong.vn/rss/nstd-giao-thong-do-thi-244.rss": {
    "etag": "0e035a6adb1788997b88cf6c1a13f7bb",
    "last_modified": null,
    "fetched_at": 1756395794,
    "status": 200,
    "error": ""
  },
  "https://tienphong.vn/rss/nstd-moi-truong-313.rss": {
    "etag": "478300e750ecd64e62e44bc63cda911e",
    "last_modified": null,
    "fetched_at": 1756395794,
    "status": 200
  },
  "https://tienphong.vn/rss/song-xanh-dau-tu-444.rss": {
    "etag": "75a8486ddca61d273cbc681f40b07be1",
    "last_modified": null,
    "fetched_at": 1756395794,
    "status": 200
  },
  "https://vovlive.vn/rss/kinh-te/kinh-te-xanh": {
    "etag": null,
    "last_modified": null,
    "fetched_at": 1756395794,
    "status": 200
  },
  "https://vovlive.vn/rss/thoi-su/an-ninh-quoc-phong": {
    "etag": null,
    "last_modified": null,
    "fetched_at": 1756395793,
    "status": 200,
    "error": ""
  },
  "https://vovlive.vn/rss/thoi-su/moi-truong": {
    "etag": null,
    "last_modified": null,
    "fetched_at": 1756395794,
    "status": 200
  },
  "https://vovlive.vn/rss/tin-tuc/kinh-te": {
    "etag": null,
    "last_modified": null,
    "fetched_at": 1756395794,
    "status": 200,
    "error": ""
  },
  "https://vovlive.vn/rss/vov-giao-thong-do-thi/vov-giao-thong-nhip-cau-giao-thong": {
    "etag": null,
    "last_modified": null,
    "fetched_at": 1756395794,
    "status": 200,
    "error": ""
  },
  "https://vovlive.vn/rss/vov-giao-thong-hot-news/vov-giao-thong-nhat-ky-do-thi": {
    "etag": null,
    "last_modified": null,
    "fetched_at": 1756395794,
    "status": 200,
    "error": ""
  },
  "https://vovlive.vn/rss/vov-giao-thong/vov-giao-thong-do-thi": {
    "etag": null,
    "last_modified": null,
    "fetched_at": 1756395794,
    "status": 200
  },
  "https://vovlive.vn/rss/vov1-khoc-hoc-cong-nghe/vov1-tai-nguyen-va-moi-truong": {
    "etag": null,
    "last_modified": null,
    "fetched_at": 1756395793,
    "status": 200
  },
  "https://vovlive.vn/rss/vov1-kinh-te/vov1-dong-chay-kinh-te": {
    "etag": null,
    "last_modified": null,
    "fetched_at": 1756395794,
    "status": 200
  },
  "https://vovlive.vn/rss/vov1-noi-chinh/vov1-xay-dung-dang": {
    "etag": null,
    "last_modified": null,
    "fetched_at": 1756395794,
    "status": 200
  },
  "https://vovlive.vn/rss/vov1/vov1-kinh-te": {
    "etag": null,
    "last_modified": null,
    "fetched_at": 1756395794,
    "status": 200
  },
  "https://vovlive.vn/rss/vov5/vov5-ha-noi-ngan-nam": {
    "etag": null,
    "last_modified": null,
    "fetched_at": 1756395794,
    "status": 200
  },
  "https://vovlive.vn/rss/vov5/vov5-kinh-te": {
    "etag": null,
    "last_modified": null,
    "fetched_at": 1756395794,
    "status": 200
  },
  "https://www.sggp.org.vn/rss/anninhtrattu-2.rss": {
    "etag": null,
    "last_modified": null,
    "fetched_at": 1756395795,
    "status": 200
  },
  "https://www.sggp.org.vn/rss/dautukt-37.rss": {
    "etag": null,
    "last_modified": null,
    "fetched_at": 1756395795,
    "status": 200
  },
  "https://www.sggp.org.vn/rss/kinhte-89.rss": {
    "etag": null,
    "last_modified": null,
    "fetched_at": 1756395795,
    "status": 200
  },
  "https://www.sggp.org.vn/rss/kinhtedoisong24h-421.rss": {
    "etag": null,
    "last_modified": null,
    "fetched_at": 1756395795,
    "status": 200
  },
  "https://www.sggp.org.vn/rss/quoc-phong-an-ninh-518.rss": {
    "etag": null,
    "last_modified": null,
    "fetched_at": 1756395795,
    "status": 200
  },
  "https://www.sggp.org.vn/rss/xahoi-giaothong-3.rss": {
    "etag": null,
    "last_modified": null,
    "fetched_at": 1756395795,
    "status": 200
  },
  "https://www.sggp.org.vn/rss/xahoi-gt-525.rss": {
    "etag": null,
    "last_modified": null,
    "fetched_at": 1756395795,
    "status": 200
  },
  "https://www.sggp.org.vn/rss/xahoi-moitruong-52.rss": {
    "etag": null,
    "last_modified": null,
    "fetched_at": 1756395795,
    "status": 200
  },
  "https://www.sggp.org.vn/rss/xaydungdang-204.rss": {
    "etag": null,
    "last_modified": null,
    "fetched_at": 1756395795,
    "status": 200
  },
  "https://tieudung.kinhtedothi.vn/chinh-sach-quy-hoach.rss": {
    "etag": null,
    "last_modified": null,
    "fetched_at": 1756395804,
    "status": 200,
    "error": ""
  },
  "https://tieudung.kinhtedothi.vn/vat-lieu-xay-dung.rss": {
    "etag": null,
    "last_modified": null,
    "fetched_at": 1756395798,
    "status": 200,
    "error": ""
  }
}